gapat/__init__.py
gapat/algorithms.py
gapat/processings.py
gapat/utils.py
gapat-1.1.0.dist-info/licenses/LICENSE
gapat-1.1.0.dist-info/METADATA
gapat-1.1.0.dist-info/WHEEL
gapat-1.1.0.dist-info/top_level.txt
gapat-1.1.0.dist-info/RECORD
