Metadata-Version: 2.4
Name: gapat
Version: 1.1.0
Summary: A comprehensive framework of GPU-accelerated image reconstruction for photoacoustic computed tomography
Author-email: Yibing Wang <ddffwyb@pku.edu.cn>
License: MIT License
Project-URL: homepage, https://github.com/ddffwyb/GAPAT
Keywords: photoacoustic computed tomography,large-scale data size,GPU-accelerated method,Taichi Lang for python,multiple GPU platform
Classifier: License :: OSI Approved :: MIT License
Classifier: Operating System :: OS Independent
Classifier: Programming Language :: Python :: 3
Classifier: Programming Language :: Python :: 3.8
Classifier: Programming Language :: Python :: 3.9
Classifier: Programming Language :: Python :: 3.10
Classifier: Programming Language :: Python :: 3.11
Classifier: Programming Language :: Python :: 3.12
Classifier: Programming Language :: Python :: 3.13
Requires-Python: >=3.8
License-File: LICENSE
Requires-Dist: numpy
Requires-Dist: scipy
Requires-Dist: taichi
Dynamic: license-file
